{
  "$schema": "https://json-structure.org/meta/core/v0/#",
  "$id": "https://raw.githubusercontent.com/api-evangelist/amazon-eventbridge/refs/heads/main/json-structure/amazon-eventbridge-list-event-buses-request-structure.json",
  "name": "ListEventBusesRequest",
  "description": "ListEventBusesRequest schema from Amazon EventBridge API",
  "type": "object",
  "properties": {
    "NamePrefix": {
      "type": "string"
    },
    "NextToken": {
      "type": "string"
    },
    "Limit": {
      "type": "int32"
    }
  }
}